bug_crowd/__init__.py
bug_crowd/client.py
bug_crowd/test.py
bug_crowd_api_client-3.0.0.dist-info/AUTHORS
bug_crowd_api_client-3.0.0.dist-info/LICENSE
bug_crowd_api_client-3.0.0.dist-info/METADATA
bug_crowd_api_client-3.0.0.dist-info/WHEEL
bug_crowd_api_client-3.0.0.dist-info/pbr.json
bug_crowd_api_client-3.0.0.dist-info/top_level.txt
bug_crowd_api_client-3.0.0.dist-info/RECORD
