Metadata-Version: 2.1
Name: bug-crowd-api-client
Version: 3.0.0
Summary: Python implementation of a Bugcrowd api client.
Home-page: https://github.com/asecurityteam/bug_crowd_client
Author: Atlassian Security Team
Author-email: security@atlassian.com
License: MIT
Platform: any
Classifier: Development Status :: 4 - Beta
Classifier: Environment :: Console
Classifier: Intended Audience :: Developers
Classifier: Operating System :: OS Independent
Classifier: Programming Language :: Python
Classifier: Programming Language :: Python :: 2
Classifier: Programming Language :: Python :: 2.7
Classifier: Programming Language :: Python :: 3
Classifier: Programming Language :: Python :: 3.4
Classifier: Programming Language :: Python :: 3.5
Classifier: Programming Language :: Python :: 3.6
Classifier: License :: OSI Approved :: MIT License
Requires-Dist: requests (<3.0.0,>=2.8.1)
Requires-Dist: requests-futures (<1.1.0,>=1.0.0)
Requires-Dist: six
